src/__init__.py
src/__main__.py
src/application.py
AnchorCLI-0.0.1.dist-info/LICENSE
AnchorCLI-0.0.1.dist-info/METADATA
AnchorCLI-0.0.1.dist-info/WHEEL
AnchorCLI-0.0.1.dist-info/entry_points.txt
AnchorCLI-0.0.1.dist-info/top_level.txt
AnchorCLI-0.0.1.dist-info/RECORD
